username_generator/__init__.py
username_generator/wordlists.py
username_generator-2.0.0.dist-info/DESCRIPTION.rst
username_generator-2.0.0.dist-info/METADATA
username_generator-2.0.0.dist-info/RECORD
username_generator-2.0.0.dist-info/WHEEL
username_generator-2.0.0.dist-info/entry_points.txt
username_generator-2.0.0.dist-info/metadata.json
username_generator-2.0.0.dist-info/top_level.txt
