Metadata-Version: 2.0
Name: username-generator
Version: 2.0.0
Summary: A command line application to generate random usernames.
Home-page: https://github.com/abactel/username_generator_cli
Author: Awes Mubarak
Author-email: awes.mubarak@awesmubarak.com
License: MIT
Keywords: cli random usernames
Platform: UNKNOWN
Classifier: Development Status :: 5 - Production/Stable
Classifier: Intended Audience :: Developers
Classifier: Operating System :: OS Independent
Classifier: License :: OSI Approved :: MIT License
Classifier: Programming Language :: Python
